ocbindings
scripts
