Metadata-Version: 2.4
Name: ocbindings
Version: 0.1.0
Summary: Prebuilt pyang bindings for OpenConfig models.
Author-email: João Taveira Araújo <joao@taveira.pt>
License-Expression: MIT
Project-URL: Homepage, https://github.com/jta/ocbindings
Project-URL: Repository, https://github.com/jta/ocbindings.git
Project-URL: Issues, https://github.com/jta/ocbindings/issues
Requires-Python: >=3.6
License-File: LICENSE
Requires-Dist: pyangbind>=0.8.1
Dynamic: license-file
